meter_sdk/__init__.py
meter_sdk/client.py
meter_sdk-0.5.0.dist-info/METADATA
meter_sdk-0.5.0.dist-info/WHEEL
meter_sdk-0.5.0.dist-info/top_level.txt
meter_sdk-0.5.0.dist-info/RECORD
