Metadata-Version: 2.4
Name: meter-sdk
Version: 0.5.0
Summary: Python SDK for Meter Scraper API
Author: Meter
Project-URL: Homepage, https://meter.sh
Project-URL: Documentation, https://docs.meter.sh/
Keywords: scraping,api,sdk
Classifier: Development Status :: 3 - Alpha
Classifier: Intended Audience :: Developers
Classifier: License :: OSI Approved :: MIT License
Classifier: Programming Language :: Python :: 3
Classifier: Programming Language :: Python :: 3.8
Classifier: Programming Language :: Python :: 3.9
Classifier: Programming Language :: Python :: 3.10
Classifier: Programming Language :: Python :: 3.11
Requires-Python: >=3.8
Requires-Dist: httpx>=0.24.0
Dynamic: requires-python
